hades_tool/__init__.py
hades_tool/main.py
hades_tool/scripts/README.md
hades_tool/scripts/fingerprints.json
hades_tool/scripts/hades.sh
hades_tool/scripts/payloads.txt
hades_tool/scripts/providers.json
hades_tool/scripts/regex.txt
hades_tool/scripts/resume.cfg
hades_tool/scripts/telegram_chat_id.txt
hades_tool/scripts/telegram_token.txt
hades_tool/scripts/value.txt
hades_tool/scripts/function/all-req.sh
hades_tool/scripts/function/client.sh
hades_tool/scripts/function/dir-scan.sh
hades_tool/scripts/function/m-cors.sh
hades_tool/scripts/function/m-csrf.sh
hades_tool/scripts/function/m-js.sh
hades_tool/scripts/function/m-recon.sh
hades_tool/scripts/function/m-scan.sh
hades_tool/scripts/function/m-sqli.sh
hades_tool/scripts/function/m-xss.sh
hades_tool/scripts/function/s-lfi.sh
hades_tool/scripts/function/s-port.sh
hades_tool/scripts/function/s-recon.sh
hades_tool/scripts/function/s-sqli.sh
hades_tool/scripts/function/s-xss.sh
hades_tool/scripts/function/takeover.sh
hades_tool/scripts/function/weak.sh
hades_tool/scripts/require/require.sh
hades_tool/scripts/require/resolvers.txt
hades_tool/scripts/require/gf/LICENSE
hades_tool/scripts/require/gf/LICENSE 2
hades_tool/scripts/require/gf/README 2.md
hades_tool/scripts/require/gf/README.md
hades_tool/scripts/require/gf/gf-completion 2.bash
hades_tool/scripts/require/gf/gf-completion 2.fish
hades_tool/scripts/require/gf/gf-completion 2.zsh
hades_tool/scripts/require/gf/gf-completion.bash
hades_tool/scripts/require/gf/gf-completion.fish
hades_tool/scripts/require/gf/gf-completion.zsh
hades_tool/scripts/require/gf/main 2.go
hades_tool/scripts/require/gf/main.go
hades_tool/scripts/require/gf/examples/aws-keys 2.json
hades_tool/scripts/require/gf/examples/aws-keys.json
hades_tool/scripts/require/gf/examples/base64 2.json
hades_tool/scripts/require/gf/examples/base64.json
hades_tool/scripts/require/gf/examples/cors 2.json
hades_tool/scripts/require/gf/examples/cors.json
hades_tool/scripts/require/gf/examples/debug-pages 2.json
hades_vulnscan-8.1.dist-info/METADATA
hades_vulnscan-8.1.dist-info/WHEEL
hades_vulnscan-8.1.dist-info/entry_points.txt
hades_vulnscan-8.1.dist-info/top_level.txt
hades_vulnscan-8.1.dist-info/RECORD
